LICENSE.txt
MANIFEST.in
README.md
pyproject.toml
setup.cfg
setup.py
images/Attributes_Olympic.png
olympic_sports/__init__.py
olympic_sports/parse_attributes.py
olympic_sports/read_seq.py
olympic_sports/test_read_seq.py
olympic_sports.egg-info/PKG-INFO
olympic_sports.egg-info/SOURCES.txt
olympic_sports.egg-info/dependency_links.txt
olympic_sports.egg-info/entry_points.txt
olympic_sports.egg-info/requires.txt
olympic_sports.egg-info/top_level.txt
olympic_sports/scripts/__init__.py
olympic_sports/scripts/convert_Olympic.py