Metadata-Version: 2.1
Name: olympic-sports
Version: 0.0.2
Summary: Olympic sports tools package
Home-page: https://github.com/aiporre/olympic_sports_tools
Author: Open Source
License: MIT
Platform: UNKNOWN
Classifier: Programming Language :: Python :: 3
Classifier: License :: OSI Approved :: MIT License
Classifier: Operating System :: OS Independent
